{
  "modules": [
    {
      "events": 1000,
      "label": "source",
      "mem_alloc": 62545197,
      "mem_free": 16730066,
      "time_real": 84338.858309,
      "time_thread": 83034.850204,
      "type": "PoolSource"
    },
    {
      "events": 1000,
      "label": "TriggerResults",
      "mem_alloc": 273,
      "mem_free": 23,
      "time_real": 9.212912,
      "time_thread": 9.007207,
      "type": "TriggerResultInserter"
    },
    {
      "events": 1000,
      "label": "Phase2L1GTProducer",
      "mem_alloc": 70,
      "mem_free": 23,
      "time_real": 6.770421,
      "time_thread": 6.681722,
      "type": "PathStatusInserter"
    },
    {
      "events": 1000,
      "label": "Phase2L1GTAlgoBlockProducer",
      "mem_alloc": 70,
      "mem_free": 23,
      "time_real": 4.419653,
      "time_thread": 4.401659,
      "type": "PathStatusInserter"
    },
    {
      "events": 1000,
      "label": "pDoubleEGEle37_24",
      "mem_alloc": 70,
      "mem_free": 23,
      "time_real": 10.815349,
      "time_thread": 10.62477,
      "type": "PathStatusInserter"
    },
    {
      "events": 1000,
      "label": "pDoubleIsoTkPho22_12",
      "mem_alloc": 70,
      "mem_free": 23,
      "time_real": 4.46331,
      "time_thread": 4.351479,
      "type": "PathStatusInserter"
    },
    {
      "events": 1000,
      "label": "pDoublePuppiJet112_112",
      "mem_alloc": 70,
      "mem_free": 23,
      "time_real": 3.883719,
      "time_thread": 3.868196,
      "type": "PathStatusInserter"
    },
    {
      "events": 1000,
      "label": "pDoublePuppiJet160_35_mass620",
      "mem_alloc": 70,
      "mem_free": 23,
      "time_real": 4.101362,
      "time_thread": 4.058352,
      "type": "PathStatusInserter"
    },
    {
      "events": 1000,
      "label": "pDoublePuppiTau52_52",
      "mem_alloc": 70,
      "mem_free": 23,
      "time_real": 11.883046,
      "time_thread": 11.74415,
      "type": "PathStatusInserter"
    },
    {
      "events": 1000,
      "label": "pDoubleTkEle25_12",
      "mem_alloc": 70,
      "mem_free": 23,
      "time_real": 3.94982,
      "time_thread": 3.854776,
      "type": "PathStatusInserter"
    },
    {
      "events": 1000,
      "label": "pDoubleTkElePuppiHT_8_8_390",
      "mem_alloc": 70,
      "mem_free": 23,
      "time_real": 3.288183,
      "time_thread": 3.269395,
      "type": "PathStatusInserter"
    },
    {
      "events": 1000,
      "label": "pDoubleTkMuPuppiHT_3_3_300",
      "mem_alloc": 70,
      "mem_free": 23,
      "time_real": 3.525713,
      "time_thread": 3.426311,
      "type": "PathStatusInserter"
    },
    {
      "events": 1000,
      "label": "pDoubleTkMuPuppiJetPuppiMet_3_3_60_130",
      "mem_alloc": 70,
      "mem_free": 23,
      "time_real": 3.212692,
      "time_thread": 3.230281,
      "type": "PathStatusInserter"
    },
    {
      "events": 1000,
      "label": "pDoubleTkMuon15_7",
      "mem_alloc": 70,
      "mem_free": 23,
      "time_real": 3.336023,
      "time_thread": 3.299731,
      "type": "PathStatusInserter"
    },
    {
      "events": 1000,
      "label": "pDoubleTkMuonTkEle5_5_9",
      "mem_alloc": 70,
      "mem_free": 23,
      "time_real": 3.116942,
      "time_thread": 3.03951,
      "type": "PathStatusInserter"
    },
    {
      "events": 1000,
      "label": "pDoubleTkMuon_4_4_OS_Dr1p2",
      "mem_alloc": 70,
      "mem_free": 23,
      "time_real": 3.27883,
      "time_thread": 3.220847,
      "type": "PathStatusInserter"
    },
    {
      "events": 1000,
      "label": "pDoubleTkMuon_4p5_4p5_OS_Er2_Mass7to18",
      "mem_alloc": 70,
      "mem_free": 23,
      "time_real": 3.16561,
      "time_thread": 3.126543,
      "type": "PathStatusInserter"
    },
    {
      "events": 1000,
      "label": "pDoubleTkMuon_OS_Er1p5_Dr1p4",
      "mem_alloc": 70,
      "mem_free": 23,
      "time_real": 3.213453,
      "time_thread": 3.154247,
      "type": "PathStatusInserter"
    },
    {
      "events": 1000,
      "label": "pIsoTkEleEGEle22_12",
      "mem_alloc": 70,
      "mem_free": 23,
      "time_real": 3.000089,
      "time_thread": 2.974707,
      "type": "PathStatusInserter"
    },
    {
      "events": 1000,
      "label": "pNNPuppiTauPuppiMet_55_190",
      "mem_alloc": 70,
      "mem_free": 23,
      "time_real": 2.983252,
      "time_thread": 2.975919,
      "type": "PathStatusInserter"
    },
    {
      "events": 1000,
      "label": "pPuppiHT400",
      "mem_alloc": 70,
      "mem_free": 23,
      "time_real": 3.100203,
      "time_thread": 3.047331,
      "type": "PathStatusInserter"
    },
    {
      "events": 1000,
      "label": "pPuppiHT450",
      "mem_alloc": 70,
      "mem_free": 23,
      "time_real": 3.0983,
      "time_thread": 3.045751,
      "type": "PathStatusInserter"
    },
    {
      "events": 1000,
      "label": "pPuppiMET200",
      "mem_alloc": 70,
      "mem_free": 23,
      "time_real": 2.998551,
      "time_thread": 2.973048,
      "type": "PathStatusInserter"
    },
    {
      "events": 1000,
      "label": "pPuppiMHT140",
      "mem_alloc": 70,
      "mem_free": 23,
      "time_real": 2.961764,
      "time_thread": 2.885948,
      "type": "PathStatusInserter"
    },
    {
      "events": 1000,
      "label": "pPuppiTauTkIsoEle45_22",
      "mem_alloc": 70,
      "mem_free": 23,
      "time_real": 2.951511,
      "time_thread": 2.887053,
      "type": "PathStatusInserter"
    },
    {
      "events": 1000,
      "label": "pPuppiTauTkMuon42_18",
      "mem_alloc": 70,
      "mem_free": 23,
      "time_real": 2.97707,
      "time_thread": 2.897921,
      "type": "PathStatusInserter"
    },
    {
      "events": 1000,
      "label": "pQuadJet70_55_40_40",
      "mem_alloc": 70,
      "mem_free": 23,
      "time_real": 3.516287,
      "time_thread": 3.506016,
      "type": "PathStatusInserter"
    },
    {
      "events": 1000,
      "label": "pSingleEGEle51",
      "mem_alloc": 70,
      "mem_free": 23,
      "time_real": 2.987199,
      "time_thread": 2.896754,
      "type": "PathStatusInserter"
    },
    {
      "events": 1000,
      "label": "pSingleIsoTkEle28",
      "mem_alloc": 70,
      "mem_free": 23,
      "time_real": 3.081419,
      "time_thread": 2.926857,
      "type": "PathStatusInserter"
    },
    {
      "events": 1000,
      "label": "pSingleIsoTkPho36",
      "mem_alloc": 70,
      "mem_free": 23,
      "time_real": 2.991232,
      "time_thread": 2.904699,
      "type": "PathStatusInserter"
    },
    {
      "events": 1000,
      "label": "pSinglePuppiJet230",
      "mem_alloc": 70,
      "mem_free": 23,
      "time_real": 4.763065,
      "time_thread": 4.676081,
      "type": "PathStatusInserter"
    },
    {
      "events": 1000,
      "label": "pSingleTkEle36",
      "mem_alloc": 70,
      "mem_free": 23,
      "time_real": 3.054372,
      "time_thread": 2.97227,
      "type": "PathStatusInserter"
    },
    {
      "events": 1000,
      "label": "pSingleTkMuon22",
      "mem_alloc": 70,
      "mem_free": 23,
      "time_real": 2.987908,
      "time_thread": 2.926939,
      "type": "PathStatusInserter"
    },
    {
      "events": 1000,
      "label": "pTkEleIsoPuppiHT_26_190",
      "mem_alloc": 70,
      "mem_free": 23,
      "time_real": 2.933208,
      "time_thread": 2.897705,
      "type": "PathStatusInserter"
    },
    {
      "events": 1000,
      "label": "pTkElePuppiJet_28_40_MinDR",
      "mem_alloc": 70,
      "mem_free": 23,
      "time_real": 2.906834,
      "time_thread": 2.842285,
      "type": "PathStatusInserter"
    },
    {
      "events": 1000,
      "label": "pTkEleTkMuon10_20",
      "mem_alloc": 70,
      "mem_free": 23,
      "time_real": 21.546529,
      "time_thread": 21.268818,
      "type": "PathStatusInserter"
    },
    {
      "events": 1000,
      "label": "pTkMuPuppiJetPuppiMet_3_110_120",
      "mem_alloc": 70,
      "mem_free": 23,
      "time_real": 2.998393,
      "time_thread": 2.963013,
      "type": "PathStatusInserter"
    },
    {
      "events": 1000,
      "label": "pTkMuTriPuppiJet_12_40_dRMax_DoubleJet_dEtaMax",
      "mem_alloc": 70,
      "mem_free": 23,
      "time_real": 4.368868,
      "time_thread": 4.345927,
      "type": "PathStatusInserter"
    },
    {
      "events": 1000,
      "label": "pTkMuonDoubleTkEle6_17_17",
      "mem_alloc": 70,
      "mem_free": 23,
      "time_real": 2.732045,
      "time_thread": 2.73838,
      "type": "PathStatusInserter"
    },
    {
      "events": 1000,
      "label": "pTkMuonPuppiHT6_320",
      "mem_alloc": 70,
      "mem_free": 23,
      "time_real": 2.723972,
      "time_thread": 2.68424,
      "type": "PathStatusInserter"
    },
    {
      "events": 1000,
      "label": "pTkMuonTkEle7_23",
      "mem_alloc": 70,
      "mem_free": 23,
      "time_real": 2.737373,
      "time_thread": 2.699342,
      "type": "PathStatusInserter"
    },
    {
      "events": 1000,
      "label": "pTkMuonTkIsoEle7_20",
      "mem_alloc": 70,
      "mem_free": 23,
      "time_real": 2.813538,
      "time_thread": 2.775254,
      "type": "PathStatusInserter"
    },
    {
      "events": 1000,
      "label": "pTripleTkMuon5_3_3",
      "mem_alloc": 70,
      "mem_free": 23,
      "time_real": 2.823526,
      "time_thread": 2.802506,
      "type": "PathStatusInserter"
    },
    {
      "events": 1000,
      "label": "pTripleTkMuon_5_3_0_DoubleTkMuon_5_3_OS_MassTo9",
      "mem_alloc": 70,
      "mem_free": 23,
      "time_real": 2.882222,
      "time_thread": 2.868124,
      "type": "PathStatusInserter"
    },
    {
      "events": 1000,
      "label": "pTripleTkMuon_5_3p5_2p5_OS_Mass5to17",
      "mem_alloc": 70,
      "mem_free": 23,
      "time_real": 3.261587,
      "time_thread": 3.217126,
      "type": "PathStatusInserter"
    },
    {
      "events": 1000,
      "label": "DST_HeterogeneousReco",
      "mem_alloc": 70,
      "mem_free": 23,
      "time_real": 8.381905,
      "time_thread": 8.278906,
      "type": "PathStatusInserter"
    },
    {
      "events": 1000,
      "label": "HLTriggerFinalPath",
      "mem_alloc": 70,
      "mem_free": 23,
      "time_real": 6.074367,
      "time_thread": 5.980727,
      "type": "PathStatusInserter"
    },
    {
      "events": 1000,
      "label": "HLTAnalyzerEndpath",
      "mem_alloc": 70,
      "mem_free": 23,
      "time_real": 8.078131,
      "time_thread": 7.942894,
      "type": "EndPathStatusInserter"
    },
    {
      "events": 1000,
      "label": "endjob_step",
      "mem_alloc": 70,
      "mem_free": 23,
      "time_real": 10.771158,
      "time_thread": 10.533833,
      "type": "EndPathStatusInserter"
    },
    {
      "events": 1000,
      "label": "l1tGTProducer",
      "mem_alloc": 97104,
      "mem_free": 60980,
      "time_real": 573.064987,
      "time_thread": 563.18375,
      "type": "L1GTProducer"
    },
    {
      "events": 1000,
      "label": "l1tGTAlgoBlockProducer",
      "mem_alloc": 15339,
      "mem_free": 9349,
      "time_real": 223.248907,
      "time_thread": 219.791431,
      "type": "L1GTAlgoBlockProducer"
    },
    {
      "events": 1000,
      "label": "DoubleEGEle3724",
      "mem_alloc": 70,
      "mem_free": 58,
      "time_real": 31.788776,
      "time_thread": 31.073779,
      "type": "L1GTDoubleObjectCond"
    },
    {
      "events": 1000,
      "label": "DoubleIsoTkPho2212",
      "mem_alloc": 58,
      "mem_free": 50,
      "time_real": 21.348168,
      "time_thread": 20.836659,
      "type": "L1GTDoubleObjectCond"
    },
    {
      "events": 1000,
      "label": "DoublePuppiJet112112",
      "mem_alloc": 296,
      "mem_free": 241,
      "time_real": 32.897358,
      "time_thread": 32.243701,
      "type": "L1GTDoubleObjectCond"
    },
    {
      "events": 1000,
      "label": "DoublePuppiJet16035Mass620",
      "mem_alloc": 63,
      "mem_free": 55,
      "time_real": 27.667428,
      "time_thread": 27.053332,
      "type": "L1GTDoubleObjectCond"
    },
    {
      "events": 1000,
      "label": "DoublePuppiTau5252",
      "mem_alloc": 133,
      "mem_free": 108,
      "time_real": 10.892882,
      "time_thread": 10.679457,
      "type": "L1GTDoubleObjectCond"
    },
    {
      "events": 1000,
      "label": "DoubleTkEle2512",
      "mem_alloc": 75,
      "mem_free": 61,
      "time_real": 18.73796,
      "time_thread": 18.302863,
      "type": "L1GTDoubleObjectCond"
    },
    {
      "events": 1000,
      "label": "DoubleTkElePuppiHT",
      "mem_alloc": 249,
      "mem_free": 212,
      "time_real": 35.806434,
      "time_thread": 35.17125,
      "type": "L1GTTripleObjectCond"
    },
    {
      "events": 1000,
      "label": "DoubleTkMuPuppiHT",
      "mem_alloc": 102,
      "mem_free": 90,
      "time_real": 15.805222,
      "time_thread": 15.497091,
      "type": "L1GTTripleObjectCond"
    },
    {
      "events": 1000,
      "label": "DoubleTkMuPuppiJetPuppiMet",
      "mem_alloc": 234,
      "mem_free": 215,
      "time_real": 90.725494,
      "time_thread": 88.777429,
      "type": "L1GTQuadObjectCond"
    },
    {
      "events": 1000,
      "label": "DoubleTkMuon157",
      "mem_alloc": 58,
      "mem_free": 51,
      "time_real": 8.787564,
      "time_thread": 8.559494,
      "type": "L1GTDoubleObjectCond"
    },
    {
      "events": 1000,
      "label": "DoubleTkMuonTkEle559",
      "mem_alloc": 96,
      "mem_free": 89,
      "time_real": 46.965417,
      "time_thread": 45.973488,
      "type": "L1GTTripleObjectCond"
    },
    {
      "events": 1000,
      "label": "DoubleTkMuon44OSDr1p2",
      "mem_alloc": 50,
      "mem_free": 49,
      "time_real": 8.308246,
      "time_thread": 8.154428,
      "type": "L1GTDoubleObjectCond"
    },
    {
      "events": 1000,
      "label": "DoubleTkMuon4p5OSEr2Mass7to18",
      "mem_alloc": 52,
      "mem_free": 51,
      "time_real": 8.414948,
      "time_thread": 8.199471,
      "type": "L1GTDoubleObjectCond"
    },
    {
      "events": 1000,
      "label": "DoubleTkMuonOSEr1p5Dr1p4",
      "mem_alloc": 52,
      "mem_free": 50,
      "time_real": 7.57914,
      "time_thread": 7.442962,
      "type": "L1GTDoubleObjectCond"
    },
    {
      "events": 1000,
      "label": "IsoTkEleEGEle2212",
      "mem_alloc": 151,
      "mem_free": 113,
      "time_real": 26.399754,
      "time_thread": 25.988465,
      "type": "L1GTDoubleObjectCond"
    },
    {
      "events": 1000,
      "label": "NNPuppiTauPuppiMet",
      "mem_alloc": 110,
      "mem_free": 86,
      "time_real": 8.384148,
      "time_thread": 8.248549,
      "type": "L1GTDoubleObjectCond"
    },
    {
      "events": 1000,
      "label": "PuppiHT400",
      "mem_alloc": 98,
      "mem_free": 63,
      "time_real": 5.818741,
      "time_thread": 5.743033,
      "type": "L1GTSingleObjectCond"
    },
    {
      "events": 1000,
      "label": "PuppiHT450",
      "mem_alloc": 90,
      "mem_free": 64,
      "time_real": 4.000846,
      "time_thread": 3.956738,
      "type": "L1GTSingleObjectCond"
    },
    {
      "events": 1000,
      "label": "PuppiMET200",
      "mem_alloc": 81,
      "mem_free": 66,
      "time_real": 4.083705,
      "time_thread": 4.057132,
      "type": "L1GTSingleObjectCond"
    },
    {
      "events": 1000,
      "label": "PuppiMHT140",
      "mem_alloc": 77,
      "mem_free": 66,
      "time_real": 6.771878,
      "time_thread": 6.698871,
      "type": "L1GTSingleObjectCond"
    },
    {
      "events": 1000,
      "label": "PuppiTauTkIsoEle4522",
      "mem_alloc": 133,
      "mem_free": 100,
      "time_real": 9.271008,
      "time_thread": 9.146476,
      "type": "L1GTDoubleObjectCond"
    },
    {
      "events": 1000,
      "label": "PuppiTauTkMuon4218",
      "mem_alloc": 106,
      "mem_free": 84,
      "time_real": 6.280809,
      "time_thread": 6.129565,
      "type": "L1GTDoubleObjectCond"
    },
    {
      "events": 1000,
      "label": "QuadJet70554040",
      "mem_alloc": 29815,
      "mem_free": 29672,
      "time_real": 3505.110928,
      "time_thread": 3443.828848,
      "type": "L1GTQuadObjectCond"
    },
    {
      "events": 1000,
      "label": "SingleEGEle51",
      "mem_alloc": 83,
      "mem_free": 64,
      "time_real": 4.442507,
      "time_thread": 4.388943,
      "type": "L1GTSingleObjectCond"
    },
    {
      "events": 1000,
      "label": "SingleIsoTkEle28",
      "mem_alloc": 83,
      "mem_free": 64,
      "time_real": 4.527708,
      "time_thread": 4.468278,
      "type": "L1GTSingleObjectCond"
    },
    {
      "events": 1000,
      "label": "SingleIsoTkPho36",
      "mem_alloc": 84,
      "mem_free": 64,
      "time_real": 4.415013,
      "time_thread": 4.371482,
      "type": "L1GTSingleObjectCond"
    },
    {
      "events": 1000,
      "label": "SinglePuppiJet230",
      "mem_alloc": 81,
      "mem_free": 65,
      "time_real": 4.424667,
      "time_thread": 4.332944,
      "type": "L1GTSingleObjectCond"
    },
    {
      "events": 1000,
      "label": "SingleTkEle36",
      "mem_alloc": 86,
      "mem_free": 64,
      "time_real": 4.118224,
      "time_thread": 4.047836,
      "type": "L1GTSingleObjectCond"
    },
    {
      "events": 1000,
      "label": "SingleTkMuon22",
      "mem_alloc": 86,
      "mem_free": 64,
      "time_real": 3.98607,
      "time_thread": 3.921535,
      "type": "L1GTSingleObjectCond"
    },
    {
      "events": 1000,
      "label": "TkEleIsoPuppiHT",
      "mem_alloc": 114,
      "mem_free": 84,
      "time_real": 8.080152,
      "time_thread": 7.939698,
      "type": "L1GTDoubleObjectCond"
    },
    {
      "events": 1000,
      "label": "TkElePuppiJetMinDR",
      "mem_alloc": 269,
      "mem_free": 202,
      "time_real": 25.651556,
      "time_thread": 25.067779,
      "type": "L1GTDoubleObjectCond"
    },
    {
      "events": 1000,
      "label": "TkEleTkMuon1020",
      "mem_alloc": 98,
      "mem_free": 79,
      "time_real": 9.085058,
      "time_thread": 8.86768,
      "type": "L1GTDoubleObjectCond"
    },
    {
      "events": 1000,
      "label": "TkMuPuppiJetPuppiMet",
      "mem_alloc": 223,
      "mem_free": 174,
      "time_real": 18.764098,
      "time_thread": 18.347365,
      "type": "L1GTTripleObjectCond"
    },
    {
      "events": 1000,
      "label": "TkMuTriPuppiJetdRMaxDoubleJetdEtaMax",
      "mem_alloc": 553,
      "mem_free": 499,
      "time_real": 1625.408314,
      "time_thread": 1595.758723,
      "type": "L1GTQuadObjectCond"
    },
    {
      "events": 1000,
      "label": "TkMuonDoubleTkEle61717",
      "mem_alloc": 96,
      "mem_free": 92,
      "time_real": 85.195337,
      "time_thread": 83.40304,
      "type": "L1GTTripleObjectCond"
    },
    {
      "events": 1000,
      "label": "TkMuonPuppiHT6320",
      "mem_alloc": 119,
      "mem_free": 88,
      "time_real": 5.136236,
      "time_thread": 5.012653,
      "type": "L1GTDoubleObjectCond"
    },
    {
      "events": 1000,
      "label": "TkMuonTkEle723",
      "mem_alloc": 93,
      "mem_free": 77,
      "time_real": 8.331482,
      "time_thread": 8.133391,
      "type": "L1GTDoubleObjectCond"
    },
    {
      "events": 1000,
      "label": "TkMuonTkIsoEle720",
      "mem_alloc": 86,
      "mem_free": 78,
      "time_real": 10.813675,
      "time_thread": 10.627764,
      "type": "L1GTDoubleObjectCond"
    },
    {
      "events": 1000,
      "label": "TripleTkMuon533",
      "mem_alloc": 65,
      "mem_free": 62,
      "time_real": 30.745596,
      "time_thread": 30.222908,
      "type": "L1GTTripleObjectCond"
    },
    {
      "events": 1000,
      "label": "TripleTkMuon530OSMassMax9",
      "mem_alloc": 53,
      "mem_free": 52,
      "time_real": 30.02174,
      "time_thread": 29.430126,
      "type": "L1GTTripleObjectCond"
    },
    {
      "events": 1000,
      "label": "TripleTkMuon53p52p5OSMass5to17",
      "mem_alloc": 55,
      "mem_free": 53,
      "time_real": 35.442775,
      "time_thread": 34.52403,
      "type": "L1GTTripleObjectCond"
    },
    {
      "events": 1000,
      "label": "hltTriggerType",
      "mem_alloc": 15,
      "mem_free": 15,
      "time_real": 2.539597,
      "time_thread": 2.58052,
      "type": "HLTTriggerTypeFilter"
    },
    {
      "events": 1000,
      "label": "hltOnlineBeamSpot",
      "mem_alloc": 804,
      "mem_free": 398,
      "time_real": 9.956286,
      "time_thread": 9.767251,
      "type": "BeamSpotOnlineProducer"
    },
    {
      "events": 1000,
      "label": "hltPhase2OnlineBeamSpotDevice",
      "mem_alloc": 1568,
      "mem_free": 1194,
      "time_real": 2932.256077,
      "time_thread": 55.640372,
      "type": "BeamSpotDeviceProducer@alpaka"
    },
    {
      "events": 1000,
      "label": "hltL1GTAcceptFilter",
      "mem_alloc": 15,
      "mem_free": 15,
      "time_real": 4.387267,
      "time_thread": 4.24884,
      "type": "L1GTAcceptFilter"
    },
    {
      "events": 807,
      "label": "hltPhase2SiPixelClustersSoA",
      "mem_alloc": 5635,
      "mem_free": 1771,
      "time_real": 3082.722871,
      "time_thread": 2750.984881,
      "type": "SiPixelPhase2DigiToCluster@alpaka"
    },
    {
      "events": 807,
      "label": "hltPhase2SiPixelRecHitsSoA",
      "mem_alloc": 1676,
      "mem_free": 268,
      "time_real": 1096.393862,
      "time_thread": 118.295628,
      "type": "SiPixelRecHitAlpakaPhase2@alpaka"
    },
    {
      "events": 807,
      "label": "hltSiPhase2Clusters",
      "mem_alloc": 3699965,
      "mem_free": 2604376,
      "time_real": 5533.359215,
      "time_thread": 5429.838431,
      "type": "Phase2TrackerClusterizer"
    },
    {
      "events": 807,
      "label": "hltSiPhase2RecHits",
      "mem_alloc": 57534014,
      "mem_free": 40310041,
      "time_real": 62004.290736,
      "time_thread": 61042.044938,
      "type": "Phase2TrackerRecHits"
    },
    {
      "events": 807,
      "label": "hltPhase2OtRecHitsSoA",
      "mem_alloc": 48252,
      "mem_free": 20350,
      "time_real": 11526.436017,
      "time_thread": 7341.61503,
      "type": "Phase2OTRecHitsSoAConverter@alpaka"
    },
    {
      "events": 807,
      "label": "hltPhase2PixelRecHitsExtendedSoA",
      "mem_alloc": 996,
      "mem_free": 202,
      "time_real": 1913.074846,
      "time_thread": 530.987305,
      "type": "SiPixelRecHitExtendedAlpaka@alpaka"
    },
    {
      "events": 807,
      "label": "hltExtendedPhase2PixelTracksSoA",
      "mem_alloc": 71948,
      "mem_free": 11329,
      "time_real": 4805.655779,
      "time_thread": 673.075185,
      "type": "CAHitNtupletAlpakaPhase2OT@alpaka"
    },
    {
      "events": 807,
      "label": "hltHgcalDigis",
      "mem_alloc": 58434516,
      "mem_free": 29217268,
      "time_real": 64219.081788,
      "time_thread": 63186.155597,
      "type": "HGCalRawToDigiFake"
    },
    {
      "events": 807,
      "label": "hltHGCalUncalibRecHit",
      "mem_alloc": 43951097,
      "mem_free": 24001124,
      "time_real": 58736.675063,
      "time_thread": 57900.616927,
      "type": "HGCalUncalibRecHitProducer"
    },
    {
      "events": 807,
      "label": "hltHGCalRecHit",
      "mem_alloc": 13046043,
      "mem_free": 4239,
      "time_real": 28076.37919,
      "time_thread": 27673.599226,
      "type": "HGCalRecHitProducer"
    },
    {
      "events": 807,
      "label": "hltHgcalSoARecHitsProducer",
      "mem_alloc": 28913702,
      "mem_free": 28912874,
      "time_real": 69267.008868,
      "time_thread": 66648.22754,
      "type": "HGCalSoARecHitsProducer@alpaka"
    },
    {
      "events": 807,
      "label": "hltHgcalSoARecHitsLayerClustersProducer",
      "mem_alloc": 52836,
      "mem_free": 3931,
      "time_real": 9876.396147,
      "time_thread": 4326.408595,
      "type": "HGCalSoARecHitsLayerClustersProducer@alpaka"
    },
    {
      "events": 807,
      "label": "hltHgcalSoALayerClustersProducer",
      "mem_alloc": 1283,
      "mem_free": 601,
      "time_real": 1557.743627,
      "time_thread": 1057.602795,
      "type": "HGCalSoALayerClustersProducer@alpaka"
    },
    {
      "events": 807,
      "label": "hltBoolEnd",
      "mem_alloc": 12,
      "mem_free": 12,
      "time_real": 1.712413,
      "time_thread": 1.748706,
      "type": "HLTBool"
    },
    {
      "events": 1000,
      "label": "hltTriggerSummaryAOD",
      "mem_alloc": 4789,
      "mem_free": 4601,
      "time_real": 52.375519,
      "time_thread": 51.280001,
      "type": "TriggerSummaryProducerAOD"
    },
    {
      "events": 1000,
      "label": "hltTriggerSummaryRAW",
      "mem_alloc": 1804,
      "mem_free": 23,
      "time_real": 13.134878,
      "time_thread": 12.835463,
      "type": "TriggerSummaryProducerRAW"
    },
    {
      "events": 1000,
      "label": "hltBoolFalse",
      "mem_alloc": 15,
      "mem_free": 15,
      "time_real": 2.63961,
      "time_thread": 2.682729,
      "type": "HLTBool"
    },
    {
      "events": 1000,
      "label": "hltPreHLTAnalyzerEndpath",
      "mem_alloc": 15,
      "mem_free": 15,
      "time_real": 3.708417,
      "time_thread": 3.71944,
      "type": "HLTPrescaler"
    },
    {
      "events": 1000,
      "label": "hltTrigReport",
      "mem_alloc": 15,
      "mem_free": 15,
      "time_real": 10.453913,
      "time_thread": 10.288341,
      "type": "HLTrigReport"
    },
    {
      "events": 1000,
      "label": "MEtoEDMConverter",
      "mem_alloc": 265,
      "mem_free": 265,
      "time_real": 4.146182,
      "time_thread": 4.146689,
      "type": "MEtoEDMConverter"
    },
    {
      "events": 1000,
      "label": "other",
      "mem_alloc": 66764124,
      "mem_free": 80424733,
      "time_real": 85114.549481,
      "time_thread": 47854.618336,
      "type": "other"
    },
    {
      "events": 1000,
      "label": "eventsetup",
      "mem_alloc": 2655203,
      "mem_free": 2341637,
      "time_real": 14345.230581,
      "time_thread": 10429.017954,
      "type": "eventsetup"
    },
    {
      "events": 1000,
      "label": "idle",
      "mem_alloc": 921474411,
      "mem_free": 852717114,
      "time_real": 185990.823004,
      "time_thread": 1090205.709875,
      "type": "idle"
    }
  ],
  "resources": [
    {
      "description": "real time",
      "name": "time_real",
      "title": "Time",
      "unit": "ms"
    },
    {
      "description": "cpu time",
      "name": "time_thread",
      "title": "Time",
      "unit": "ms"
    },
    {
      "description": "allocated memory",
      "name": "mem_alloc",
      "title": "Memory",
      "unit": "kB"
    },
    {
      "description": "deallocated memory",
      "name": "mem_free",
      "title": "Memory",
      "unit": "kB"
    }
  ],
  "total": {
    "events": 1000,
    "label": "HLTX",
    "mem_alloc": 1259360848,
    "mem_free": 1077413599,
    "time_real": 701399.863415,
    "time_thread": 1537117.886786,
    "type": "Job"
  }
}