{
  "modules": [
    {
      "events": 1000,
      "label": "source",
      "mem_alloc": 62543783,
      "mem_free": 16729994,
      "time_real": 84741.804775,
      "time_thread": 83357.292855,
      "type": "PoolSource"
    },
    {
      "events": 1000,
      "label": "TriggerResults",
      "mem_alloc": 273,
      "mem_free": 23,
      "time_real": 13.121157,
      "time_thread": 12.973777,
      "type": "TriggerResultInserter"
    },
    {
      "events": 1000,
      "label": "Phase2L1GTProducer",
      "mem_alloc": 70,
      "mem_free": 23,
      "time_real": 6.428799,
      "time_thread": 6.368495,
      "type": "PathStatusInserter"
    },
    {
      "events": 1000,
      "label": "Phase2L1GTAlgoBlockProducer",
      "mem_alloc": 70,
      "mem_free": 23,
      "time_real": 12.021739,
      "time_thread": 11.876547,
      "type": "PathStatusInserter"
    },
    {
      "events": 1000,
      "label": "pDoubleEGEle37_24",
      "mem_alloc": 70,
      "mem_free": 23,
      "time_real": 4.101057,
      "time_thread": 4.050835,
      "type": "PathStatusInserter"
    },
    {
      "events": 1000,
      "label": "pDoubleIsoTkPho22_12",
      "mem_alloc": 70,
      "mem_free": 23,
      "time_real": 4.22227,
      "time_thread": 4.098528,
      "type": "PathStatusInserter"
    },
    {
      "events": 1000,
      "label": "pDoublePuppiJet112_112",
      "mem_alloc": 70,
      "mem_free": 23,
      "time_real": 3.82385,
      "time_thread": 3.755,
      "type": "PathStatusInserter"
    },
    {
      "events": 1000,
      "label": "pDoublePuppiJet160_35_mass620",
      "mem_alloc": 70,
      "mem_free": 23,
      "time_real": 3.84992,
      "time_thread": 3.805687,
      "type": "PathStatusInserter"
    },
    {
      "events": 1000,
      "label": "pDoublePuppiTau52_52",
      "mem_alloc": 70,
      "mem_free": 23,
      "time_real": 3.91717,
      "time_thread": 3.844766,
      "type": "PathStatusInserter"
    },
    {
      "events": 1000,
      "label": "pDoubleTkEle25_12",
      "mem_alloc": 70,
      "mem_free": 23,
      "time_real": 3.681402,
      "time_thread": 3.639034,
      "type": "PathStatusInserter"
    },
    {
      "events": 1000,
      "label": "pDoubleTkElePuppiHT_8_8_390",
      "mem_alloc": 70,
      "mem_free": 23,
      "time_real": 3.317777,
      "time_thread": 3.298125,
      "type": "PathStatusInserter"
    },
    {
      "events": 1000,
      "label": "pDoubleTkMuPuppiHT_3_3_300",
      "mem_alloc": 70,
      "mem_free": 23,
      "time_real": 3.305192,
      "time_thread": 3.225722,
      "type": "PathStatusInserter"
    },
    {
      "events": 1000,
      "label": "pDoubleTkMuPuppiJetPuppiMet_3_3_60_130",
      "mem_alloc": 70,
      "mem_free": 23,
      "time_real": 3.147068,
      "time_thread": 3.116403,
      "type": "PathStatusInserter"
    },
    {
      "events": 1000,
      "label": "pDoubleTkMuon15_7",
      "mem_alloc": 70,
      "mem_free": 23,
      "time_real": 3.293034,
      "time_thread": 3.226585,
      "type": "PathStatusInserter"
    },
    {
      "events": 1000,
      "label": "pDoubleTkMuonTkEle5_5_9",
      "mem_alloc": 70,
      "mem_free": 23,
      "time_real": 2.967369,
      "time_thread": 2.92712,
      "type": "PathStatusInserter"
    },
    {
      "events": 1000,
      "label": "pDoubleTkMuon_4_4_OS_Dr1p2",
      "mem_alloc": 70,
      "mem_free": 23,
      "time_real": 3.082314,
      "time_thread": 3.055309,
      "type": "PathStatusInserter"
    },
    {
      "events": 1000,
      "label": "pDoubleTkMuon_4p5_4p5_OS_Er2_Mass7to18",
      "mem_alloc": 70,
      "mem_free": 23,
      "time_real": 3.066758,
      "time_thread": 3.041807,
      "type": "PathStatusInserter"
    },
    {
      "events": 1000,
      "label": "pDoubleTkMuon_OS_Er1p5_Dr1p4",
      "mem_alloc": 70,
      "mem_free": 23,
      "time_real": 11.773225,
      "time_thread": 11.681195,
      "type": "PathStatusInserter"
    },
    {
      "events": 1000,
      "label": "pIsoTkEleEGEle22_12",
      "mem_alloc": 70,
      "mem_free": 23,
      "time_real": 2.986188,
      "time_thread": 2.918817,
      "type": "PathStatusInserter"
    },
    {
      "events": 1000,
      "label": "pNNPuppiTauPuppiMet_55_190",
      "mem_alloc": 70,
      "mem_free": 23,
      "time_real": 2.988871,
      "time_thread": 2.949683,
      "type": "PathStatusInserter"
    },
    {
      "events": 1000,
      "label": "pPuppiHT400",
      "mem_alloc": 70,
      "mem_free": 23,
      "time_real": 3.025873,
      "time_thread": 2.936759,
      "type": "PathStatusInserter"
    },
    {
      "events": 1000,
      "label": "pPuppiHT450",
      "mem_alloc": 70,
      "mem_free": 23,
      "time_real": 3.024268,
      "time_thread": 2.933363,
      "type": "PathStatusInserter"
    },
    {
      "events": 1000,
      "label": "pPuppiMET200",
      "mem_alloc": 70,
      "mem_free": 23,
      "time_real": 2.907096,
      "time_thread": 2.881783,
      "type": "PathStatusInserter"
    },
    {
      "events": 1000,
      "label": "pPuppiMHT140",
      "mem_alloc": 70,
      "mem_free": 23,
      "time_real": 2.873356,
      "time_thread": 2.828526,
      "type": "PathStatusInserter"
    },
    {
      "events": 1000,
      "label": "pPuppiTauTkIsoEle45_22",
      "mem_alloc": 70,
      "mem_free": 23,
      "time_real": 2.833014,
      "time_thread": 2.814662,
      "type": "PathStatusInserter"
    },
    {
      "events": 1000,
      "label": "pPuppiTauTkMuon42_18",
      "mem_alloc": 70,
      "mem_free": 23,
      "time_real": 2.902911,
      "time_thread": 2.876449,
      "type": "PathStatusInserter"
    },
    {
      "events": 1000,
      "label": "pQuadJet70_55_40_40",
      "mem_alloc": 70,
      "mem_free": 23,
      "time_real": 3.468582,
      "time_thread": 3.440708,
      "type": "PathStatusInserter"
    },
    {
      "events": 1000,
      "label": "pSingleEGEle51",
      "mem_alloc": 70,
      "mem_free": 23,
      "time_real": 2.955116,
      "time_thread": 2.877918,
      "type": "PathStatusInserter"
    },
    {
      "events": 1000,
      "label": "pSingleIsoTkEle28",
      "mem_alloc": 70,
      "mem_free": 23,
      "time_real": 2.995181,
      "time_thread": 2.88778,
      "type": "PathStatusInserter"
    },
    {
      "events": 1000,
      "label": "pSingleIsoTkPho36",
      "mem_alloc": 70,
      "mem_free": 23,
      "time_real": 2.910245,
      "time_thread": 2.884575,
      "type": "PathStatusInserter"
    },
    {
      "events": 1000,
      "label": "pSinglePuppiJet230",
      "mem_alloc": 70,
      "mem_free": 23,
      "time_real": 2.887934,
      "time_thread": 2.850148,
      "type": "PathStatusInserter"
    },
    {
      "events": 1000,
      "label": "pSingleTkEle36",
      "mem_alloc": 70,
      "mem_free": 23,
      "time_real": 2.902835,
      "time_thread": 2.851005,
      "type": "PathStatusInserter"
    },
    {
      "events": 1000,
      "label": "pSingleTkMuon22",
      "mem_alloc": 70,
      "mem_free": 23,
      "time_real": 2.838418,
      "time_thread": 2.810013,
      "type": "PathStatusInserter"
    },
    {
      "events": 1000,
      "label": "pTkEleIsoPuppiHT_26_190",
      "mem_alloc": 70,
      "mem_free": 23,
      "time_real": 2.934509,
      "time_thread": 2.876619,
      "type": "PathStatusInserter"
    },
    {
      "events": 1000,
      "label": "pTkElePuppiJet_28_40_MinDR",
      "mem_alloc": 70,
      "mem_free": 23,
      "time_real": 2.832048,
      "time_thread": 2.788578,
      "type": "PathStatusInserter"
    },
    {
      "events": 1000,
      "label": "pTkEleTkMuon10_20",
      "mem_alloc": 70,
      "mem_free": 23,
      "time_real": 2.827436,
      "time_thread": 2.780085,
      "type": "PathStatusInserter"
    },
    {
      "events": 1000,
      "label": "pTkMuPuppiJetPuppiMet_3_110_120",
      "mem_alloc": 70,
      "mem_free": 23,
      "time_real": 2.857824,
      "time_thread": 2.838479,
      "type": "PathStatusInserter"
    },
    {
      "events": 1000,
      "label": "pTkMuTriPuppiJet_12_40_dRMax_DoubleJet_dEtaMax",
      "mem_alloc": 70,
      "mem_free": 23,
      "time_real": 3.266683,
      "time_thread": 3.217065,
      "type": "PathStatusInserter"
    },
    {
      "events": 1000,
      "label": "pTkMuonDoubleTkEle6_17_17",
      "mem_alloc": 70,
      "mem_free": 23,
      "time_real": 2.757753,
      "time_thread": 2.709305,
      "type": "PathStatusInserter"
    },
    {
      "events": 1000,
      "label": "pTkMuonPuppiHT6_320",
      "mem_alloc": 70,
      "mem_free": 23,
      "time_real": 2.699244,
      "time_thread": 2.678877,
      "type": "PathStatusInserter"
    },
    {
      "events": 1000,
      "label": "pTkMuonTkEle7_23",
      "mem_alloc": 70,
      "mem_free": 23,
      "time_real": 2.628716,
      "time_thread": 2.627353,
      "type": "PathStatusInserter"
    },
    {
      "events": 1000,
      "label": "pTkMuonTkIsoEle7_20",
      "mem_alloc": 70,
      "mem_free": 23,
      "time_real": 2.704557,
      "time_thread": 2.642254,
      "type": "PathStatusInserter"
    },
    {
      "events": 1000,
      "label": "pTripleTkMuon5_3_3",
      "mem_alloc": 70,
      "mem_free": 23,
      "time_real": 5.246861,
      "time_thread": 5.100423,
      "type": "PathStatusInserter"
    },
    {
      "events": 1000,
      "label": "pTripleTkMuon_5_3_0_DoubleTkMuon_5_3_OS_MassTo9",
      "mem_alloc": 70,
      "mem_free": 23,
      "time_real": 2.898582,
      "time_thread": 2.837492,
      "type": "PathStatusInserter"
    },
    {
      "events": 1000,
      "label": "pTripleTkMuon_5_3p5_2p5_OS_Mass5to17",
      "mem_alloc": 70,
      "mem_free": 23,
      "time_real": 6.358069,
      "time_thread": 6.178858,
      "type": "PathStatusInserter"
    },
    {
      "events": 1000,
      "label": "DST_HeterogeneousReco",
      "mem_alloc": 70,
      "mem_free": 23,
      "time_real": 13.005239,
      "time_thread": 12.885843,
      "type": "PathStatusInserter"
    },
    {
      "events": 1000,
      "label": "HLTriggerFinalPath",
      "mem_alloc": 70,
      "mem_free": 23,
      "time_real": 3.590893,
      "time_thread": 3.540235,
      "type": "PathStatusInserter"
    },
    {
      "events": 1000,
      "label": "HLTAnalyzerEndpath",
      "mem_alloc": 70,
      "mem_free": 23,
      "time_real": 7.318243,
      "time_thread": 7.188663,
      "type": "EndPathStatusInserter"
    },
    {
      "events": 1000,
      "label": "endjob_step",
      "mem_alloc": 70,
      "mem_free": 23,
      "time_real": 7.487441,
      "time_thread": 7.328537,
      "type": "EndPathStatusInserter"
    },
    {
      "events": 1000,
      "label": "l1tGTProducer",
      "mem_alloc": 97104,
      "mem_free": 60980,
      "time_real": 551.687564,
      "time_thread": 540.892306,
      "type": "L1GTProducer"
    },
    {
      "events": 1000,
      "label": "l1tGTAlgoBlockProducer",
      "mem_alloc": 15337,
      "mem_free": 9347,
      "time_real": 141.020958,
      "time_thread": 138.7146,
      "type": "L1GTAlgoBlockProducer"
    },
    {
      "events": 1000,
      "label": "DoubleEGEle3724",
      "mem_alloc": 71,
      "mem_free": 59,
      "time_real": 26.106477,
      "time_thread": 25.69889,
      "type": "L1GTDoubleObjectCond"
    },
    {
      "events": 1000,
      "label": "DoubleIsoTkPho2212",
      "mem_alloc": 59,
      "mem_free": 51,
      "time_real": 23.556643,
      "time_thread": 23.174951,
      "type": "L1GTDoubleObjectCond"
    },
    {
      "events": 1000,
      "label": "DoublePuppiJet112112",
      "mem_alloc": 296,
      "mem_free": 241,
      "time_real": 28.297548,
      "time_thread": 27.832087,
      "type": "L1GTDoubleObjectCond"
    },
    {
      "events": 1000,
      "label": "DoublePuppiJet16035Mass620",
      "mem_alloc": 63,
      "mem_free": 56,
      "time_real": 26.707079,
      "time_thread": 26.190438,
      "type": "L1GTDoubleObjectCond"
    },
    {
      "events": 1000,
      "label": "DoublePuppiTau5252",
      "mem_alloc": 134,
      "mem_free": 109,
      "time_real": 10.550197,
      "time_thread": 10.373441,
      "type": "L1GTDoubleObjectCond"
    },
    {
      "events": 1000,
      "label": "DoubleTkEle2512",
      "mem_alloc": 76,
      "mem_free": 62,
      "time_real": 18.150223,
      "time_thread": 17.793448,
      "type": "L1GTDoubleObjectCond"
    },
    {
      "events": 1000,
      "label": "DoubleTkElePuppiHT",
      "mem_alloc": 249,
      "mem_free": 213,
      "time_real": 38.892067,
      "time_thread": 38.272686,
      "type": "L1GTTripleObjectCond"
    },
    {
      "events": 1000,
      "label": "DoubleTkMuPuppiHT",
      "mem_alloc": 102,
      "mem_free": 90,
      "time_real": 13.785929,
      "time_thread": 13.475838,
      "type": "L1GTTripleObjectCond"
    },
    {
      "events": 1000,
      "label": "DoubleTkMuPuppiJetPuppiMet",
      "mem_alloc": 230,
      "mem_free": 211,
      "time_real": 86.830915,
      "time_thread": 84.882444,
      "type": "L1GTQuadObjectCond"
    },
    {
      "events": 1000,
      "label": "DoubleTkMuon157",
      "mem_alloc": 59,
      "mem_free": 52,
      "time_real": 17.121644,
      "time_thread": 16.862305,
      "type": "L1GTDoubleObjectCond"
    },
    {
      "events": 1000,
      "label": "DoubleTkMuonTkEle559",
      "mem_alloc": 97,
      "mem_free": 91,
      "time_real": 48.537214,
      "time_thread": 47.51939,
      "type": "L1GTTripleObjectCond"
    },
    {
      "events": 1000,
      "label": "DoubleTkMuon44OSDr1p2",
      "mem_alloc": 51,
      "mem_free": 50,
      "time_real": 9.473675,
      "time_thread": 9.276981,
      "type": "L1GTDoubleObjectCond"
    },
    {
      "events": 1000,
      "label": "DoubleTkMuon4p5OSEr2Mass7to18",
      "mem_alloc": 52,
      "mem_free": 51,
      "time_real": 8.111846,
      "time_thread": 7.955045,
      "type": "L1GTDoubleObjectCond"
    },
    {
      "events": 1000,
      "label": "DoubleTkMuonOSEr1p5Dr1p4",
      "mem_alloc": 52,
      "mem_free": 50,
      "time_real": 12.692225,
      "time_thread": 12.481859,
      "type": "L1GTDoubleObjectCond"
    },
    {
      "events": 1000,
      "label": "IsoTkEleEGEle2212",
      "mem_alloc": 151,
      "mem_free": 113,
      "time_real": 23.049767,
      "time_thread": 22.587156,
      "type": "L1GTDoubleObjectCond"
    },
    {
      "events": 1000,
      "label": "NNPuppiTauPuppiMet",
      "mem_alloc": 109,
      "mem_free": 85,
      "time_real": 9.202411,
      "time_thread": 9.094701,
      "type": "L1GTDoubleObjectCond"
    },
    {
      "events": 1000,
      "label": "PuppiHT400",
      "mem_alloc": 98,
      "mem_free": 63,
      "time_real": 4.218218,
      "time_thread": 4.152091,
      "type": "L1GTSingleObjectCond"
    },
    {
      "events": 1000,
      "label": "PuppiHT450",
      "mem_alloc": 90,
      "mem_free": 64,
      "time_real": 3.876525,
      "time_thread": 3.831535,
      "type": "L1GTSingleObjectCond"
    },
    {
      "events": 1000,
      "label": "PuppiMET200",
      "mem_alloc": 80,
      "mem_free": 65,
      "time_real": 3.907426,
      "time_thread": 3.813728,
      "type": "L1GTSingleObjectCond"
    },
    {
      "events": 1000,
      "label": "PuppiMHT140",
      "mem_alloc": 77,
      "mem_free": 66,
      "time_real": 7.934124,
      "time_thread": 7.799415,
      "type": "L1GTSingleObjectCond"
    },
    {
      "events": 1000,
      "label": "PuppiTauTkIsoEle4522",
      "mem_alloc": 133,
      "mem_free": 100,
      "time_real": 9.684944,
      "time_thread": 9.504212,
      "type": "L1GTDoubleObjectCond"
    },
    {
      "events": 1000,
      "label": "PuppiTauTkMuon4218",
      "mem_alloc": 107,
      "mem_free": 86,
      "time_real": 8.632215,
      "time_thread": 8.489546,
      "type": "L1GTDoubleObjectCond"
    },
    {
      "events": 1000,
      "label": "QuadJet70554040",
      "mem_alloc": 29815,
      "mem_free": 29672,
      "time_real": 3588.888177,
      "time_thread": 3524.523875,
      "type": "L1GTQuadObjectCond"
    },
    {
      "events": 1000,
      "label": "SingleEGEle51",
      "mem_alloc": 83,
      "mem_free": 64,
      "time_real": 4.481278,
      "time_thread": 4.363647,
      "type": "L1GTSingleObjectCond"
    },
    {
      "events": 1000,
      "label": "SingleIsoTkEle28",
      "mem_alloc": 83,
      "mem_free": 65,
      "time_real": 4.450311,
      "time_thread": 4.31793,
      "type": "L1GTSingleObjectCond"
    },
    {
      "events": 1000,
      "label": "SingleIsoTkPho36",
      "mem_alloc": 84,
      "mem_free": 64,
      "time_real": 15.868405,
      "time_thread": 15.487696,
      "type": "L1GTSingleObjectCond"
    },
    {
      "events": 1000,
      "label": "SinglePuppiJet230",
      "mem_alloc": 82,
      "mem_free": 66,
      "time_real": 4.512484,
      "time_thread": 4.430321,
      "type": "L1GTSingleObjectCond"
    },
    {
      "events": 1000,
      "label": "SingleTkEle36",
      "mem_alloc": 86,
      "mem_free": 64,
      "time_real": 4.169208,
      "time_thread": 4.085428,
      "type": "L1GTSingleObjectCond"
    },
    {
      "events": 1000,
      "label": "SingleTkMuon22",
      "mem_alloc": 86,
      "mem_free": 64,
      "time_real": 3.830725,
      "time_thread": 3.763239,
      "type": "L1GTSingleObjectCond"
    },
    {
      "events": 1000,
      "label": "TkEleIsoPuppiHT",
      "mem_alloc": 113,
      "mem_free": 83,
      "time_real": 6.034889,
      "time_thread": 5.906907,
      "type": "L1GTDoubleObjectCond"
    },
    {
      "events": 1000,
      "label": "TkElePuppiJetMinDR",
      "mem_alloc": 268,
      "mem_free": 202,
      "time_real": 23.614662,
      "time_thread": 23.233231,
      "type": "L1GTDoubleObjectCond"
    },
    {
      "events": 1000,
      "label": "TkEleTkMuon1020",
      "mem_alloc": 98,
      "mem_free": 79,
      "time_real": 14.009472,
      "time_thread": 13.800152,
      "type": "L1GTDoubleObjectCond"
    },
    {
      "events": 1000,
      "label": "TkMuPuppiJetPuppiMet",
      "mem_alloc": 223,
      "mem_free": 174,
      "time_real": 15.838995,
      "time_thread": 15.477474,
      "type": "L1GTTripleObjectCond"
    },
    {
      "events": 1000,
      "label": "TkMuTriPuppiJetdRMaxDoubleJetdEtaMax",
      "mem_alloc": 553,
      "mem_free": 498,
      "time_real": 1656.364883,
      "time_thread": 1625.369655,
      "type": "L1GTQuadObjectCond"
    },
    {
      "events": 1000,
      "label": "TkMuonDoubleTkEle61717",
      "mem_alloc": 96,
      "mem_free": 92,
      "time_real": 98.624889,
      "time_thread": 96.703308,
      "type": "L1GTTripleObjectCond"
    },
    {
      "events": 1000,
      "label": "TkMuonPuppiHT6320",
      "mem_alloc": 119,
      "mem_free": 87,
      "time_real": 7.00319,
      "time_thread": 6.782329,
      "type": "L1GTDoubleObjectCond"
    },
    {
      "events": 1000,
      "label": "TkMuonTkEle723",
      "mem_alloc": 94,
      "mem_free": 78,
      "time_real": 7.977964,
      "time_thread": 7.897322,
      "type": "L1GTDoubleObjectCond"
    },
    {
      "events": 1000,
      "label": "TkMuonTkIsoEle720",
      "mem_alloc": 85,
      "mem_free": 77,
      "time_real": 8.750996,
      "time_thread": 8.641725,
      "type": "L1GTDoubleObjectCond"
    },
    {
      "events": 1000,
      "label": "TripleTkMuon533",
      "mem_alloc": 64,
      "mem_free": 61,
      "time_real": 36.405375,
      "time_thread": 35.814661,
      "type": "L1GTTripleObjectCond"
    },
    {
      "events": 1000,
      "label": "TripleTkMuon530OSMassMax9",
      "mem_alloc": 54,
      "mem_free": 53,
      "time_real": 29.985201,
      "time_thread": 29.302175,
      "type": "L1GTTripleObjectCond"
    },
    {
      "events": 1000,
      "label": "TripleTkMuon53p52p5OSMass5to17",
      "mem_alloc": 54,
      "mem_free": 51,
      "time_real": 34.852312,
      "time_thread": 34.003822,
      "type": "L1GTTripleObjectCond"
    },
    {
      "events": 1000,
      "label": "hltTriggerType",
      "mem_alloc": 15,
      "mem_free": 15,
      "time_real": 2.472685,
      "time_thread": 2.505276,
      "type": "HLTTriggerTypeFilter"
    },
    {
      "events": 1000,
      "label": "hltOnlineBeamSpot",
      "mem_alloc": 804,
      "mem_free": 398,
      "time_real": 10.346921,
      "time_thread": 10.254279,
      "type": "BeamSpotOnlineProducer"
    },
    {
      "events": 1000,
      "label": "hltPhase2OnlineBeamSpotDevice",
      "mem_alloc": 1823,
      "mem_free": 1333,
      "time_real": 2441.239626,
      "time_thread": 50.165918,
      "type": "BeamSpotDeviceProducer@alpaka"
    },
    {
      "events": 1000,
      "label": "hltL1GTAcceptFilter",
      "mem_alloc": 15,
      "mem_free": 15,
      "time_real": 3.933454,
      "time_thread": 3.932416,
      "type": "L1GTAcceptFilter"
    },
    {
      "events": 807,
      "label": "hltPhase2SiPixelClustersSoA",
      "mem_alloc": 5145,
      "mem_free": 1521,
      "time_real": 2955.053478,
      "time_thread": 2649.031841,
      "type": "SiPixelPhase2DigiToCluster@alpaka"
    },
    {
      "events": 807,
      "label": "hltPhase2SiPixelRecHitsSoA",
      "mem_alloc": 1667,
      "mem_free": 264,
      "time_real": 928.232539,
      "time_thread": 106.141731,
      "type": "SiPixelRecHitAlpakaPhase2@alpaka"
    },
    {
      "events": 807,
      "label": "hltSiPhase2Clusters",
      "mem_alloc": 3699965,
      "mem_free": 2604376,
      "time_real": 5682.291849,
      "time_thread": 5567.686092,
      "type": "Phase2TrackerClusterizer"
    },
    {
      "events": 807,
      "label": "hltSiPhase2RecHits",
      "mem_alloc": 57534014,
      "mem_free": 40310041,
      "time_real": 64376.321602,
      "time_thread": 63358.058594,
      "type": "Phase2TrackerRecHits"
    },
    {
      "events": 807,
      "label": "hltPhase2OtRecHitsSoA",
      "mem_alloc": 48683,
      "mem_free": 20371,
      "time_real": 11547.626229,
      "time_thread": 7003.87974,
      "type": "Phase2OTRecHitsSoAConverter@alpaka"
    },
    {
      "events": 807,
      "label": "hltPhase2PixelRecHitsExtendedSoA",
      "mem_alloc": 958,
      "mem_free": 198,
      "time_real": 2394.221572,
      "time_thread": 527.646011,
      "type": "SiPixelRecHitExtendedAlpaka@alpaka"
    },
    {
      "events": 807,
      "label": "hltExtendedPhase2PixelTracksSoA",
      "mem_alloc": 73009,
      "mem_free": 11788,
      "time_real": 5399.934141,
      "time_thread": 644.774518,
      "type": "CAHitNtupletAlpakaPhase2OT@alpaka"
    },
    {
      "events": 807,
      "label": "hltHgcalDigis",
      "mem_alloc": 58434516,
      "mem_free": 29217268,
      "time_real": 66293.64141,
      "time_thread": 65086.401634,
      "type": "HGCalRawToDigiFake"
    },
    {
      "events": 807,
      "label": "hltHGCalUncalibRecHit",
      "mem_alloc": 43951097,
      "mem_free": 24001124,
      "time_real": 59669.215518,
      "time_thread": 58761.031289,
      "type": "HGCalUncalibRecHitProducer"
    },
    {
      "events": 807,
      "label": "hltHGCalRecHit",
      "mem_alloc": 13046043,
      "mem_free": 4244,
      "time_real": 28643.160136,
      "time_thread": 28212.920738,
      "type": "HGCalRecHitProducer"
    },
    {
      "events": 807,
      "label": "hltHgcalSoARecHitsProducer",
      "mem_alloc": 28913710,
      "mem_free": 28912878,
      "time_real": 69849.656253,
      "time_thread": 67499.583857,
      "type": "HGCalSoARecHitsProducer@alpaka"
    },
    {
      "events": 807,
      "label": "hltHgcalSoARecHitsLayerClustersProducer",
      "mem_alloc": 52071,
      "mem_free": 3425,
      "time_real": 9542.761165,
      "time_thread": 4146.323675,
      "type": "HGCalSoARecHitsLayerClustersProducer@alpaka"
    },
    {
      "events": 807,
      "label": "hltHgcalSoALayerClustersProducer",
      "mem_alloc": 1293,
      "mem_free": 600,
      "time_real": 1424.372934,
      "time_thread": 1052.148813,
      "type": "HGCalSoALayerClustersProducer@alpaka"
    },
    {
      "events": 807,
      "label": "hltBoolEnd",
      "mem_alloc": 12,
      "mem_free": 12,
      "time_real": 1.672706,
      "time_thread": 1.690705,
      "type": "HLTBool"
    },
    {
      "events": 1000,
      "label": "hltTriggerSummaryAOD",
      "mem_alloc": 4789,
      "mem_free": 4601,
      "time_real": 50.17227,
      "time_thread": 49.173589,
      "type": "TriggerSummaryProducerAOD"
    },
    {
      "events": 1000,
      "label": "hltTriggerSummaryRAW",
      "mem_alloc": 1804,
      "mem_free": 23,
      "time_real": 12.193103,
      "time_thread": 11.977831,
      "type": "TriggerSummaryProducerRAW"
    },
    {
      "events": 1000,
      "label": "hltBoolFalse",
      "mem_alloc": 15,
      "mem_free": 15,
      "time_real": 2.833764,
      "time_thread": 2.846008,
      "type": "HLTBool"
    },
    {
      "events": 1000,
      "label": "hltPreHLTAnalyzerEndpath",
      "mem_alloc": 15,
      "mem_free": 15,
      "time_real": 3.501076,
      "time_thread": 3.515183,
      "type": "HLTPrescaler"
    },
    {
      "events": 1000,
      "label": "hltTrigReport",
      "mem_alloc": 15,
      "mem_free": 15,
      "time_real": 9.528625,
      "time_thread": 9.34159,
      "type": "HLTrigReport"
    },
    {
      "events": 1000,
      "label": "MEtoEDMConverter",
      "mem_alloc": 265,
      "mem_free": 265,
      "time_real": 4.060459,
      "time_thread": 3.957855,
      "type": "MEtoEDMConverter"
    },
    {
      "events": 1000,
      "label": "other",
      "mem_alloc": 66735695,
      "mem_free": 83254836,
      "time_real": 86743.019837,
      "time_thread": 48281.464881,
      "type": "other"
    },
    {
      "events": 1000,
      "label": "eventsetup",
      "mem_alloc": 2655195,
      "mem_free": 2341627,
      "time_real": 14285.950415,
      "time_thread": 9939.047299,
      "type": "eventsetup"
    },
    {
      "events": 1000,
      "label": "idle",
      "mem_alloc": 892956699,
      "mem_free": 836097252,
      "time_real": 184955.46768,
      "time_thread": 1050024.275117,
      "type": "idle"
    }
  ],
  "resources": [
    {
      "description": "real time",
      "name": "time_real",
      "title": "Time",
      "unit": "ms"
    },
    {
      "description": "cpu time",
      "name": "time_thread",
      "title": "Time",
      "unit": "ms"
    },
    {
      "description": "allocated memory",
      "name": "mem_alloc",
      "title": "Memory",
      "unit": "kB"
    },
    {
      "description": "deallocated memory",
      "name": "mem_free",
      "title": "Memory",
      "unit": "kB"
    }
  ],
  "total": {
    "events": 1000,
    "label": "HLTX",
    "mem_alloc": 1230813746,
    "mem_free": 1063623623,
    "time_real": 708877.411559,
    "time_thread": 1503143.589115,
    "type": "Job"
  }
}